txt2detection/__init__.py
txt2detection/__main__.py
txt2detection/attack_navigator.py
txt2detection/bundler.py
txt2detection/credential_checker.py
txt2detection/models.py
txt2detection/observables.py
txt2detection/utils.py
txt2detection/ai_extractor/__init__.py
txt2detection/ai_extractor/anthropic.py
txt2detection/ai_extractor/base.py
txt2detection/ai_extractor/deepseek.py
txt2detection/ai_extractor/gemini.py
txt2detection/ai_extractor/openai.py
txt2detection/ai_extractor/openrouter.py
txt2detection/ai_extractor/prompts.py
txt2detection/ai_extractor/utils.py
txt2detection/config/detection_languages.yaml
txt2detection-1.1.12.dist-info/METADATA
txt2detection-1.1.12.dist-info/WHEEL
txt2detection-1.1.12.dist-info/entry_points.txt
txt2detection-1.1.12.dist-info/licenses/LICENSE
txt2detection-1.1.12.dist-info/RECORD
