Metadata-Version: 2.4
Name: txt2detection
Version: 1.1.12
Summary: A command line tool that takes a txt file containing threat intelligence and turns it into a detection rule.
Project-URL: Homepage, https://github.com/muchdogesec/txt2detection
Project-URL: Issues, https://github.com/muchdogesec/txt2detection/issues
Project-URL: dogesec HQ, https://dogesec.com
Author: dogesec
Maintainer: dogesec
License-File: LICENSE
Classifier: License :: OSI Approved :: Apache Software License
Classifier: Operating System :: OS Independent
Classifier: Programming Language :: Python :: 3
Requires-Python: >=3.11
Requires-Dist: json-repair
Requires-Dist: jsonschema>=4.22.0; python_version >= '3.8'
Requires-Dist: llama-index-core>=0.14.8
Requires-Dist: llama-index-llms-openai>=0.6.8
Requires-Dist: python-arango>=8.1.3; python_version >= '3.8'
Requires-Dist: python-dotenv>=1.0.1
Requires-Dist: python-slugify
Requires-Dist: pyyaml
Requires-Dist: requests>=2.31.0; python_version >= '3.7'
Requires-Dist: stix2
Requires-Dist: stix2extensions
Requires-Dist: tqdm>=4.66.4; python_version >= '3.7'
Requires-Dist: validators>=0.34.0
Provides-Extra: anthropic
Requires-Dist: llama-index-llms-anthropic>=0.9.7; extra == 'anthropic'
Provides-Extra: deepseek
Requires-Dist: llama-index-llms-deepseek>=0.2.2; extra == 'deepseek'
Provides-Extra: gemini
Requires-Dist: llama-index-llms-google-genai>=0.5.0; extra == 'gemini'
Provides-Extra: llms
Requires-Dist: llama-index-llms-anthropic>=0.9.7; extra == 'llms'
Requires-Dist: llama-index-llms-deepseek>=0.2.2; extra == 'llms'
Requires-Dist: llama-index-llms-google-genai>=0.5.0; extra == 'llms'
Requires-Dist: llama-index-llms-openrouter>=0.4.2; extra == 'llms'
Provides-Extra: openrouter
Requires-Dist: llama-index-llms-openrouter>=0.4.2; extra == 'openrouter'
